{
    "name": "item.cobblemon.ability_patch",
    "category": "cobblepedia:items",
    "read_by_default": true,
    "icon": "cobblemon:ability_patch",
    "pages": [
        {
            "type": "patchouli:spotlight",
            "item": "cobblemon:ability_patch",
            "link_recipe": true,
            "text": "book.cobblepedia.entries.ability_patch.text"
        },
        {
            "type": "patchouli:text",
            "title": "book.cobblepedia.pages.obtaining",
            "text": "book.cobblepedia.entries.ability_patch.obtaining.text"
        }
    ]
}
