{
    "name": "item.cobblemon.max_potion",
    "category": "cobblepedia:items",
    "read_by_default": true,
    "icon": "cobblemon:max_potion",
    "pages": [
        {
            "type": "patchouli:spotlight",
            "item": "cobblemon:max_potion",
            "text": "book.cobblepedia.entries.max_potion.text"
        },
        {
            "type": "cobblepedia:brewing",
            "title": "book.cobblepedia.pages.brewing",
            "reagent_item": "cobblemon:vivichoke",
            "base_item": "cobblemon:hyper_potion",
            "result_item": "cobblemon:max_potion"
        },
        {
            "type": "patchouli:relations",
            "title": "book.cobblepedia.pages.brewing_ingredient",
            "entries": [
                "cobblepedia:full_restore"
            ]
        }
    ]
}
